{
  "product": [
    {
      "name": "Vy Quan",
      "price": "557.00",
      "desc": "The automobile layout consists of a front-engine design, with transaxle-type transmissions mounted at the rear of the engine and four wheel drive",
      "img": "https://firebasestorage.googleapis.com/v0/b/angular-78b50.appspot.com/o/img%2Fshowcase-3.png?alt=media&token=75e669c5-0fe7-4fb7-9511-1b47528e0854",
      "status": false,
      "id": "1"
    },
    {
      "name": "Nancy Walker",
      "price": "602.00",
      "desc": "Ergonomic executive chair upholstered in bonded black leather and PVC padded seat and back for all-day comfort and support",
      "img": "https://firebasestorage.googleapis.com/v0/b/angular-78b50.appspot.com/o/img%2Fshowcase-3.png?alt=media&token=75e669c5-0fe7-4fb7-9511-1b47528e0854",
      "status": true,
      "id": "2"
    },
    {
      "name": "Mae Aufderhar",
      "price": "888.00",
      "desc": "The beautiful range of Apple Naturalé that has an exciting mix of natural ingredients. With the Goodness of 100% Natural Ingredients",
      "img": "https://firebasestorage.googleapis.com/v0/b/angular-78b50.appspot.com/o/img%2Fshowcase-3.png?alt=media&token=75e669c5-0fe7-4fb7-9511-1b47528e0854",
      "status": false,
      "id": "3"
    },
    {
      "name": "Mrs. Olive Rempel",
      "price": "238.00",
      "desc": "Carbonite web goalkeeper gloves are ergonomically designed to give easy fit",
      "img": "https://firebasestorage.googleapis.com/v0/b/angular-78b50.appspot.com/o/img%2Fshowcase-3.png?alt=media&token=75e669c5-0fe7-4fb7-9511-1b47528e0854",
      "status": true,
      "id": "4"
    },
    {
      "name": "Christy Fritsch V",
      "price": "519.00",
      "desc": "The Football Is Good For Training And Recreational Purposes",
      "img": "https://firebasestorage.googleapis.com/v0/b/angular-78b50.appspot.com/o/img%2Fshowcase-3.png?alt=media&token=75e669c5-0fe7-4fb7-9511-1b47528e0854",
      "status": true,
      "id": "5"
    },
    {
      "name": "Nancy Mitchell",
      "price": "499.00",
      "desc": "New range of formal shirts are designed keeping you in mind. With fits and styling that will make you stand apart",
      "img": "https://firebasestorage.googleapis.com/v0/b/angular-78b50.appspot.com/o/img%2Fshowcase-3.png?alt=media&token=75e669c5-0fe7-4fb7-9511-1b47528e0854",
      "status": false,
      "id": "6"
    },
    {
      "name": "Jonathon Kshlerin",
      "price": "544.00",
      "desc": "Carbonite web goalkeeper gloves are ergonomically designed to give easy fit",
      "img": "https://firebasestorage.googleapis.com/v0/b/angular-78b50.appspot.com/o/img%2Fshowcase-3.png?alt=media&token=75e669c5-0fe7-4fb7-9511-1b47528e0854",
      "status": false,
      "id": "7"
    },
    {
      "name": "Jasmine Reichert",
      "price": "455.00",
      "desc": "The Apollotech B340 is an affordable wireless mouse with reliable connectivity, 12 months battery life and modern design",
      "img": "https://firebasestorage.googleapis.com/v0/b/angular-78b50.appspot.com/o/img%2Fshowcase-3.png?alt=media&token=75e669c5-0fe7-4fb7-9511-1b47528e0854",
      "status": false,
      "id": "8"
    },
    {
      "name": "Rose Crist",
      "price": "463.00",
      "desc": "The Apollotech B340 is an affordable wireless mouse with reliable connectivity, 12 months battery life and modern design",
      "img": "https://firebasestorage.googleapis.com/v0/b/angular-78b50.appspot.com/o/img%2Fshowcase-3.png?alt=media&token=75e669c5-0fe7-4fb7-9511-1b47528e0854",
      "status": true,
      "id": "9"
    },
    {
      "name": "Thelma Pacocha",
      "price": "592.00",
      "desc": "Carbonite web goalkeeper gloves are ergonomically designed to give easy fit",
      "img": "https://firebasestorage.googleapis.com/v0/b/angular-78b50.appspot.com/o/img%2Fshowcase-3.png?alt=media&token=75e669c5-0fe7-4fb7-9511-1b47528e0854",
      "status": true,
      "id": "10"
    },
    {
      "name": "James Nicolas",
      "price": "443.00",
      "desc": "New ABC 13 9370, 13.3, 5th Gen CoreA5-8250U, 8GB RAM, 256GB SSD, power UHD Graphics, OS 10 Home, OS Office A & J 2016",
      "img": "https://firebasestorage.googleapis.com/v0/b/angular-78b50.appspot.com/o/img%2Fshowcase-3.png?alt=media&token=75e669c5-0fe7-4fb7-9511-1b47528e0854",
      "status": false,
      "id": "11"
    },
    {
      "name": "Margaret McLaughlin",
      "price": "988.00",
      "desc": "New ABC 13 9370, 13.3, 5th Gen CoreA5-8250U, 8GB RAM, 256GB SSD, power UHD Graphics, OS 10 Home, OS Office A & J 2016",
      "img": "https://firebasestorage.googleapis.com/v0/b/angular-78b50.appspot.com/o/img%2Fshowcase-3.png?alt=media&token=75e669c5-0fe7-4fb7-9511-1b47528e0854",
      "status": false,
      "id": "12"
    },
    {
      "name": "Antonia Spencer MD",
      "price": "803.00",
      "desc": "Andy shoes are designed to keeping in mind durability as well as trends, the most stylish range of shoes & sandals",
      "img": "https://firebasestorage.googleapis.com/v0/b/angular-78b50.appspot.com/o/img%2Fshowcase-3.png?alt=media&token=75e669c5-0fe7-4fb7-9511-1b47528e0854",
      "status": true,
      "id": "13"
    },
    {
      "name": "Toni Wilderman",
      "price": "746.00",
      "desc": "The Nagasaki Lander is the trademarked name of several series of Nagasaki sport bikes, that started with the 1984 ABC800J",
      "img": "https://firebasestorage.googleapis.com/v0/b/angular-78b50.appspot.com/o/img%2Fshowcase-3.png?alt=media&token=75e669c5-0fe7-4fb7-9511-1b47528e0854",
      "status": false,
      "id": "14"
    },
    {
      "name": "Alexis Gaylord",
      "price": "440.00",
      "desc": "The slim & simple Maple Gaming Keyboard from Dev Byte comes with a sleek body and 7- Color RGB LED Back-lighting for smart functionality",
      "img": "https://firebasestorage.googleapis.com/v0/b/angular-78b50.appspot.com/o/img%2Fshowcase-3.png?alt=media&token=75e669c5-0fe7-4fb7-9511-1b47528e0854",
      "status": false,
      "id": "15"
    },
    {
      "name": "Franklin Koss",
      "price": "883.00",
      "desc": "The slim & simple Maple Gaming Keyboard from Dev Byte comes with a sleek body and 7- Color RGB LED Back-lighting for smart functionality",
      "img": "https://firebasestorage.googleapis.com/v0/b/angular-78b50.appspot.com/o/img%2Fshowcase-3.png?alt=media&token=75e669c5-0fe7-4fb7-9511-1b47528e0854",
      "status": false,
      "id": "16"
    }
  ],
  "category": [
    {
      "name": "Apple Watch"
    }
  ]
}